ddot/__init__.py
ddot/__main__.py
ddot/lib.py
pyproject.toml
ddot-0.4.0.dist-info/entry_points.txt
ddot-0.4.0.dist-info/LICENSE
ddot-0.4.0.dist-info/WHEEL
ddot-0.4.0.dist-info/METADATA
ddot-0.4.0.dist-info/RECORD
