Metadata-Version: 2.1
Name: ddot
Version: 0.4.0
Summary: Dotfile manager using the Devinstaller framework
Home-page: https://justine.kizhak.com/projects/ddot
License: MIT
Author: Justine Kizhakkinedath
Author-email: justine@kizhak.com
Requires-Python: >=3.8,<4.0
Classifier: Development Status :: 3 - Alpha
Classifier: Intended Audience :: Developers
Classifier: Intended Audience :: Information Technology
Classifier: Intended Audience :: System Administrators
Classifier: License :: OSI Approved :: MIT License
Classifier: Operating System :: OS Independent
Classifier: Programming Language :: Python :: 3
Classifier: Programming Language :: Python :: 3.8
Classifier: Programming Language :: Python :: 3.9
Classifier: Typing :: Typed
Requires-Dist: devinstaller-core (>=0.9.1,<0.10.0)
Requires-Dist: typer (>=0.3.2,<0.4.0)
Project-URL: Bug Reports, https://gitlab.com/justinekizhak/ddot/issues
Project-URL: Repository, https://gitlab.com/justinekizhak/ddot
Project-URL: Say Thanks!, https://saythanks.io/to/justine%40kizhak.com
